jklint/__init__.py
jklint/call.py
jklint/cli.py
jklint-0.0.2.dist-info/LICENSE
jklint-0.0.2.dist-info/METADATA
jklint-0.0.2.dist-info/WHEEL
jklint-0.0.2.dist-info/entry_points.txt
jklint-0.0.2.dist-info/top_level.txt
jklint-0.0.2.dist-info/RECORD
