Metadata-Version: 2.1
Name: jklint
Version: 0.0.2
Summary: A CLI designed to save time linting and validating Jenkinsfiles.
Home-page: https://github.com/aissa-laribi/jklint
Author: Aissa Laribi
Author-email: aissalaribi@yahoo.fr
License: UNKNOWN
Platform: UNKNOWN
Requires-Dist: coverage (==6.5.0)
Requires-Dist: python-dotenv (==0.21.0)
Requires-Dist: requests (==2.28.1)
